lame/__init__.py
lame/hip.cpython-39-darwin.so
streamp3/__init__.py
streamp3-0.1.12.dist-info/LICENSE
streamp3-0.1.12.dist-info/METADATA
streamp3-0.1.12.dist-info/WHEEL
streamp3-0.1.12.dist-info/top_level.txt
streamp3-0.1.12.dist-info/RECORD
