Metadata-Version: 2.1
Name: streamp3
Version: 0.1.12
Summary: streaming mp3 decoder
Home-page: https://github.com/pylon/streamp3/
Author: Brent M. Spell
Author-email: brent@pylon.com
License: UNKNOWN
Platform: UNKNOWN
Classifier: Programming Language :: Python :: 3
Classifier: License :: OSI Approved :: Apache Software License
Classifier: Operating System :: OS Independent
License-File: LICENSE
Requires-Dist: Cython (==0.29.34)
